{"cameraMode":{"drawMode":0,"name":"Shaded","section":"Shading Mode"},"sceneLighting":true,"audioPlay":false,"sceneViewState":{"m_AlwaysRefresh":false,"showFog":true,"showSkybox":true,"showFlares":true,"showImageEffects":true,"showParticleSystems":true,"showVisualEffectGraphs":true,"m_FxEnabled":true},"in2DMode":false,"pivot":{"x":-55.12082290649414,"y":-6.911750793457031,"z":-16.76599884033203},"rotation":{"x":-0.5966221690177918,"y":0.006498229689896107,"z":-0.004831214435398579,"w":-0.8024804592132568},"size":17.851694107055665,"orthographic":false}